asuscharge/__init__.py
asuscharge/__main__.py
asuscharge/_version.py
asus_charge_control-1.0.3.dist-info/LICENCE
asus_charge_control-1.0.3.dist-info/METADATA
asus_charge_control-1.0.3.dist-info/WHEEL
asus_charge_control-1.0.3.dist-info/entry_points.txt
asus_charge_control-1.0.3.dist-info/top_level.txt
asus_charge_control-1.0.3.dist-info/RECORD
