Metadata-Version: 2.1
Name: asus-charge-control
Version: 1.0.3
Summary: Set your recent ASUS notebook's maximum charge level on Linux.
Home-page: https://github.com/cforrester1988/asus-charge-control
Author: Christopher Forrester
Author-email: christopher@cforrester.ca
License: GPLv3+
Platform: UNKNOWN
Classifier: Environment :: Console
Classifier: Intended Audience :: End Users/Desktop
Classifier: License :: OSI Approved :: GNU General Public License v3 or later (GPLv3+)
Classifier: Natural Language :: English
Classifier: Operating System :: POSIX :: Linux
Classifier: Programming Language :: Python :: 3
Classifier: Programming Language :: Python :: 3.7
Classifier: Topic :: Utilities
Requires-Python: >=3.7
